{"timeout": true, "paths": 0, "flatBoolVars": 1296, "flatIntVars": 120, "flatBoolConstraints": 662, "flatIntConstraints": 1156, "evaluatedReifiedConstraints": 1416, "method": "satisfy", "flatTime": 0.414639, "nSolutions": 0, "nodes": 25718642, "failures": 17388749, "restarts": 0, "variables": 2749, "intVars": 128, "boolVariables": 2619, "propagators": 2097, "propagations": 7829546882, "peakDepth": 44, "nogoods": 17388749, "backjumps": 8329864, "peakMem": 0.0, "time": 3600.061, "initTime": 0.06, "solveTime": 3600.001, "baseMem": 0.0, "trailMem": 0.05, "randomSeed": 1}