{"timeout": false, "paths": 0, "flatBoolVars": 26474, "flatIntVars": 26474, "flatIntConstraints": 29174, "method": "satisfy", "flatTime": 0.85814, "nSolutions": 1, "nodes": 29003, "failures": 26398, "restarts": 0, "variables": 185846, "intVars": 26474, "boolVariables": 159370, "propagators": 5401, "propagations": 20019453, "peakDepth": 47, "nogoods": 26398, "backjumps": 2567, "peakMem": 0.0, "time": 21.929, "initTime": 0.466, "solveTime": 21.463, "baseMem": 0.0, "trailMem": 0.42, "randomSeed": 1668960055}