{"timeout": true, "paths": 0, "flatBoolVars": 1092, "flatIntVars": 1079, "flatBoolConstraints": 728, "flatIntConstraints": 2017, "evaluatedHalfReifiedConstraints": 1092, "method": "minimize", "flatTime": 0.829168, "nodes": 683671, "failures": 479511, "restarts": 1035, "variables": 88913, "intVars": 1261, "boolVariables": 87650, "propagators": 1613, "propagations": 258871629, "peakDepth": 131, "nogoods": 479511, "backjumps": 157761, "peakMem": 0.0, "time": 300.084, "initTime": 0.084, "solveTime": 300.0, "objective": 472, "optTime": 277.765, "baseMem": 0.0, "trailMem": 0.19, "randomSeed": 1668726207, "nSolutions": 1}