{"timeout": false, "paths": 0, "flatBoolVars": 715, "flatIntVars": 72, "flatBoolConstraints": 404, "flatIntConstraints": 633, "evaluatedReifiedConstraints": 789, "method": "satisfy", "flatTime": 0.323009, "nSolutions": 1, "nodes": 60954, "failures": 58195, "restarts": 0, "variables": 1596, "intVars": 79, "boolVariables": 1515, "propagators": 1096, "propagations": 15206692, "peakDepth": 26, "nogoods": 58195, "backjumps": 2739, "peakMem": 0.0, "time": 7.271, "initTime": 0.033, "solveTime": 7.238, "baseMem": 0.0, "trailMem": 0.02, "randomSeed": 7}