{"timeout": false, "paths": 0, "flatBoolVars": 26474, "flatIntVars": 26474, "flatIntConstraints": 29174, "method": "satisfy", "flatTime": 0.855094, "nSolutions": 1, "nodes": 230053, "failures": 168049, "restarts": 392, "variables": 185846, "intVars": 26474, "boolVariables": 159370, "propagators": 5401, "propagations": 108289387, "peakDepth": 123, "nogoods": 168049, "backjumps": 36965, "peakMem": 0.0, "time": 177.658, "initTime": 0.476, "solveTime": 177.182, "baseMem": 0.0, "trailMem": 0.42, "randomSeed": 1669156449}