{"timeout": true, "paths": 0, "flatBoolVars": 2635, "flatIntVars": 264, "flatBoolConstraints": 1428, "flatIntConstraints": 2329, "evaluatedReifiedConstraints": 2901, "method": "satisfy", "flatTime": 0.610751, "nSolutions": 0, "nodes": 17730185, "failures": 16738612, "restarts": 0, "variables": 5792, "intVars": 272, "boolVariables": 5518, "propagators": 3912, "propagations": 12201635014, "peakDepth": 79, "nogoods": 16738612, "backjumps": 991520, "peakMem": 0.0, "time": 3600.117, "initTime": 0.109, "solveTime": 3600.008, "baseMem": 0.0, "trailMem": 0.12, "randomSeed": 12}