{"timeout": true, "paths": 0, "flatBoolVars": 3376, "flatIntVars": 312, "flatBoolConstraints": 1686, "flatIntConstraints": 3012, "evaluatedReifiedConstraints": 3688, "method": "satisfy", "flatTime": 0.725493, "nSolutions": 0, "nodes": 25175353, "failures": 15236097, "restarts": 0, "variables": 7133, "intVars": 328, "boolVariables": 6803, "propagators": 5393, "propagations": 9969922642, "peakDepth": 94, "nogoods": 15236097, "backjumps": 9939170, "peakMem": 0.0, "time": 3600.145, "initTime": 0.145, "solveTime": 3600.0, "baseMem": 0.0, "trailMem": 0.12, "randomSeed": 1}